README.rst
setup.py
pysentiment/__init__.py
pysentiment/base.py
pysentiment/hiv4.py
pysentiment/lm.py
pysentiment/utils.py
pysentiment.egg-info/PKG-INFO
pysentiment.egg-info/SOURCES.txt
pysentiment.egg-info/dependency_links.txt
pysentiment.egg-info/requires.txt
pysentiment.egg-info/top_level.txt
pysentiment/static/Currencies.txt
pysentiment/static/DatesandNumbers.txt
pysentiment/static/Generic.txt
pysentiment/static/Geographic.txt
pysentiment/static/HIV-4.csv
pysentiment/static/LM.csv
pysentiment/static/Names.txt