Metadata-Version: 1.0
Name: pysentiment
Version: 0.1.2.0
Summary: Python sentiment analysis utilities
Home-page: UNKNOWN
Author: Zhichao HAN
Author-email: hanzhichao@gmail.com
License: UNKNOWN
Platform: UNKNOWN
